<?xml version="1.0" ?>
<openerp>
	<data>
		
		<!-- Curriculum -->
		<menuitem id="iu_curriculum_main_menu"
			name="Curriculums"
			sequence="1"
			parent="iuopensys_core.major_core_menu"
			action="iu_curriculum_main_action"/>		
	
		<!-- Semester Section -->
		<menuitem id="semester_main_menu"
			name="Semesters"
			sequence="1"
			parent="iuopensys_core.academic_core_menu"
			action="semester_main_action"/>
			
		<!-- Course Section -->	
		<menuitem id="course_core_menu"
			name="Course Management"
			sequence="3"
			parent="iuopensys_core.academic_core_menu"/>
			
		<menuitem id="course_main_menu"
			name="Courses"
			sequence="0"
			parent="course_core_menu"
			action="course_main_action"/>
			
		<menuitem id="offer_course_main_menu"
			name="Offering Courses"
			sequence="1"
			parent="course_core_menu"
			action="offer_course_main_action"/>
			
		<!-- Study Periods -->
		<menuitem id="study_period_main_menu"
			name="Course Schedules"
			sequence="2"
			parent="course_core_menu"
			action="study_period_main_action"/>
			
		<!-- Course Registration Config Section -->
		<menuitem id="course_registration_core_menu"
			name="Registration"
			sequence="1"
			parent="iuopensys_core.academic_root_menu"/>
		
		<menuitem id="course_registration_main_menu"
			name="Registration Management"
			sequence="0"
			parent="course_registration_core_menu"
			action="course_registration_main_action"/>
			
		<!-- Student Course Registration -->
		<menuitem id="student_course_main_menu"
			name="Student Registrations"
			sequence="3"
			parent="course_registration_core_menu"
			action="student_course_main_action"/>
			
		<!-- Registration Form -->
		<menuitem id="student_registration_core_menu"
			name="Enrollment"
			sequence="1"
			parent="iuopensys_core.student_root_menu"/>
			
		<menuitem id="student_registration_main_menu"
			name="Student Registration"
			sequence="0"
			parent="student_registration_core_menu"
			action="student_registration_main_action"/>
		
			
		<!-- Student Tuition -->
		<menuitem id="student_registration_tuition_menu"
			name="Student Tuition"
			sequence="4"
			parent="course_registration_core_menu"
			action="student_registration_tuition_action"/>
			
		<!-- Student Academic Program -->
		<menuitem id="student_academic_program_menu"
			name="Academic Program"
			sequence="2"
			parent="iuopensys_core.major_core_menu"
			action="student_academic_program_main_action"/>
		
		<!-- Miscellaneous -->
		<menuitem id="miscellaneous_core_menu"
			name="Misc."
			sequence="4"	
			parent="iuopensys_core.university_root_menu"/>
		
		<!-- Partner University -->
		<menuitem id="partner_university_main_menu"
			name="Partner Universities"
			sequence="0"
			parent="miscellaneous_core_menu"
			action="partner_university_main_action"/>
		
		<!-- Documents -->
		<menuitem id="iu_document_core_menu"
			name="Document"
			sequence="2"
			parent="miscellaneous_core_menu"/>
			
		<!-- IU Documents -->
		<menuitem id="iu_document_main_menu"
			name="Documents"
			sequence="0"
			parent="iu_document_core_menu"
			action="iu_document_main_action"/>
			
		<!-- Course Tuition -->
		<menuitem id="course_tuition_main_menu"
			name="Course Tuition"
			sequence="5"
			parent="miscellaneous_core_menu"
			action="course_tuition_main_action"/>
		
		<!-- Student's Documents -->
		<menuitem id="student_document_core_main_menu"
			name="Student Documents"
			sequence="1"
			parent="iu_document_core_menu"
			action="student_document_main_action"/>
			
		<!-- Financial Aids -->
		<menuitem id="financial_aid_main_menu"
			name="Financial Aids"
			sequence="1"
			parent="miscellaneous_core_menu"
			action="financial_aid_main_action"/>
			
		<!-- <menuitem id="student_behavior_point_main_menu"
			name="Behavior Point"
			sequence="1"
			parent="iuopensys_core.student_core_menu"
			action="student_behavior_point_main_action"/> -->
			
		<!-- Student Semester -->
		<menuitem id="academic_management_core_menu"
			name="Student Academic"
			sequence="0"
			parent="iuopensys_core.academic_root_menu"/>
			
		<!-- Student Behavior System -->
		<menuitem id="student_semester_behavior_point_main_menu"
			name="Behavior Point"
			sequence="2"
			parent="academic_management_core_menu"
			groups="iuopensys_core.group_staff"
			action="student_semester_behavior_point_main_action"/>
		
		<menuitem id="student_semester_main_menu"
			name="Semester Transcript"
			sequence="1"
			parent="academic_management_core_menu"
			action="student_semester_main_action"/>	
			
		<!-- <delete model="ir.ui.menu" id="mail.mail_channel_menu_root_chat"/> -->
 		<menuitem id="student_financial_aid_main_menu"
			name="Student Financial Aid"
			sequence="4"
			parent="iuopensys_core.student_core_menu"
			action="student_financial_aid_main_action"/>
		
	</data>
</openerp>
